brep_to_h5m/__init__.py
brep_to_h5m/_version.py
brep_to_h5m/core.py
brep_to_h5m-0.4.2.dist-info/LICENSE.txt
brep_to_h5m-0.4.2.dist-info/METADATA
brep_to_h5m-0.4.2.dist-info/WHEEL
brep_to_h5m-0.4.2.dist-info/top_level.txt
brep_to_h5m-0.4.2.dist-info/RECORD
