Metadata-Version: 2.1
Name: brep-to-h5m
Version: 0.4.2
Summary: Converts Brep CAD geometry files to h5m geometry files compatible with DAGMC simulations
Author-email: Jonathan Shimwell <mail@jshimwell.com>
License: MIT License        
Project-URL: Homepage, https://github.com/fusion-energy/brep_to_h5m
Project-URL: Bug Tracker, https://github.com/fusion-energy/brep_to_h5m/issues
Keywords: dagmc,geometry,plot,slice
Classifier: Programming Language :: Python :: 3
Classifier: License :: OSI Approved :: MIT License
Classifier: Operating System :: OS Independent
Requires-Python: >=3.8
License-File: LICENSE.txt
Requires-Dist: trimesh
Requires-Dist: networkx
Requires-Dist: stl-to-h5m
Requires-Dist: vertices-to-h5m
Provides-Extra: tests
Requires-Dist: pytest ; extra == 'tests'
Requires-Dist: pytest-cov ; extra == 'tests'
Requires-Dist: brep-part-finder ; extra == 'tests'
Requires-Dist: dagmc-h5m-file-inspector ; extra == 'tests'
Requires-Dist: openmc-data-downloader ; extra == 'tests'
